docs/dali_bench.py
site/dali_bench.py
triton_augment/__init__.py
triton_augment/__main__.py
triton_augment/config.py
triton_augment/functional.py
triton_augment/transforms.py
triton_augment/utils.py
triton_augment/kernels/__init__.py
triton_augment/kernels/color_normalize_kernel.py
triton_augment/kernels/fused_kernel.py
triton_augment/kernels/geometric_kernel.py
triton_augment-0.2.0.dist-info/licenses/LICENSE
triton_augment-0.2.0.dist-info/METADATA
triton_augment-0.2.0.dist-info/WHEEL
triton_augment-0.2.0.dist-info/top_level.txt
triton_augment-0.2.0.dist-info/RECORD
