Metadata-Version: 2.4
Name: triton-augment
Version: 0.2.0
Summary: GPU-accelerated image augmentation with kernel fusion using Triton
Home-page: https://github.com/yuhezhang-ai/triton-augment
Author: yuhezhang-ai
Author-email: Yuhe Zhang <yuhezhang.zju@gmail.com>
License: Apache-2.0
Project-URL: Homepage, https://github.com/yuhezhang-ai/triton-augment
Project-URL: Documentation, https://github.com/yuhezhang-ai/triton-augment#readme
Project-URL: Repository, https://github.com/yuhezhang-ai/triton-augment
Project-URL: Bug Tracker, https://github.com/yuhezhang-ai/triton-augment/issues
Keywords: pytorch,triton,gpu,augmentation,image-processing,deep-learning
Classifier: Development Status :: 3 - Alpha
Classifier: Intended Audience :: Developers
Classifier: Intended Audience :: Science/Research
Classifier: License :: OSI Approved :: Apache Software License
Classifier: Programming Language :: Python :: 3
Classifier: Programming Language :: Python :: 3.8
Classifier: Programming Language :: Python :: 3.9
Classifier: Programming Language :: Python :: 3.10
Classifier: Programming Language :: Python :: 3.11
Classifier: Topic :: Scientific/Engineering :: Artificial Intelligence
Classifier: Topic :: Scientific/Engineering :: Image Processing
Requires-Python: >=3.8
License-File: LICENSE
Requires-Dist: torch>=2.0.0
Requires-Dist: triton>=2.0.0
Provides-Extra: dev
Requires-Dist: pytest>=7.0.0; extra == "dev"
Requires-Dist: pytest-benchmark>=4.0.0; extra == "dev"
Requires-Dist: pytest-cov>=4.0.0; extra == "dev"
Requires-Dist: torchvision>=0.15.0; extra == "dev"
Requires-Dist: pillow>=9.0.0; extra == "dev"
Requires-Dist: matplotlib>=3.5.0; extra == "dev"
Requires-Dist: black>=23.0.0; extra == "dev"
Requires-Dist: flake8>=6.0.0; extra == "dev"
Requires-Dist: mypy>=1.0.0; extra == "dev"
Requires-Dist: isort>=5.12.0; extra == "dev"
Provides-Extra: examples
Requires-Dist: torchvision>=0.15.0; extra == "examples"
Requires-Dist: pillow>=9.0.0; extra == "examples"
Requires-Dist: matplotlib>=3.5.0; extra == "examples"
Dynamic: author
Dynamic: home-page
Dynamic: license-file
Dynamic: requires-python
